{
	"miniprogramRoot": "miniprogram/",
	"cloudfunctionRoot": "cloudfunctions/",
	"setting": {
		"urlCheck": true,
		"es6": true,
		"postcss": true,
		"minified": true,
		"newFeature": true,
		"enhance": true
	},
	"appid": "wx05f813a3409cda8f",
	"projectname": "miniprogram-1",
	"libVersion": "2.8.1",
	"simulatorType": "wechat",
	"simulatorPluginLibVersion": {},
	"condition": {
		"search": {
			"current": -1,
			"list": []
		},
		"conversation": {
			"current": -1,
			"list": []
		},
		"plugin": {
			"current": -1,
			"list": []
		},
		"game": {
			"list": []
		},
		"gamePlugin": {
			"current": -1,
			"list": []
		},
		"miniprogram": {
			"current": 0,
			"list": [
				{
					"id": -1,
					"name": "db guide",
					"pathName": "pages/databaseGuide/databaseGuide",
					"query": ""
				},
				{
					"id": -1,
					"name": "pages/home/home",
					"pathName": "pages/home/home",
					"query": "",
					"scene": null
				},
				{
					"id": -1,
					"name": "pages/profile/profile",
					"pathName": "pages/profile/profile",
					"query": "",
					"scene": null
				},
				{
					"id": -1,
					"name": "pages/publish/publish",
					"pathName": "pages/publish/publish",
					"query": "",
					"scene": null
				},
				{
					"id": -1,
					"name": "pages/communication/communication",
					"pathName": "pages/communication/communication",
					"scene": null
				}
			]
		}
	}
}